authenticator/__init__.py
authenticator/cli.py
authenticator/data.py
authenticator/hotp.py
authenticator-1.1.3.dist-info/DESCRIPTION.rst
authenticator-1.1.3.dist-info/METADATA
authenticator-1.1.3.dist-info/RECORD
authenticator-1.1.3.dist-info/WHEEL
authenticator-1.1.3.dist-info/entry_points.txt
authenticator-1.1.3.dist-info/metadata.json
authenticator-1.1.3.dist-info/top_level.txt
