Metadata-Version: 1.1
Name: authenticator
Version: 1.1.3
Summary: A HOTP/TOTP code generator for the command line.
Home-page: https://github.com/JeNeSuisPasDave/authenticator
Author: Dave Hein
Author-email: dhein@acm.org
License: MIT
Keywords: tfa mfa authenticator hotp totp
Platform: UNKNOWN
Classifier: Development Status :: 5 - Production/Stable
Classifier: Intended Audience :: End Users/Desktop
Classifier: Topic :: Security
Classifier: License :: OSI Approved :: MIT License
Classifier: Programming Language :: Python :: 3
Classifier: Programming Language :: Python :: 3.5
